president/__init__.py
president/__main__.py
president/_version.py
president/alignment.py
president/sequence.py
president/statistics.py
president/writer.py
pypresident-0.6.8.dist-info/LICENSE
pypresident-0.6.8.dist-info/METADATA
pypresident-0.6.8.dist-info/WHEEL
pypresident-0.6.8.dist-info/entry_points.txt
pypresident-0.6.8.dist-info/top_level.txt
pypresident-0.6.8.dist-info/RECORD
