Metadata-Version: 2.1
Name: pypresident
Version: 0.6.8
Summary: PaiRwisE Sequence IDENtiTy. Calculate pairwise nucleotide identitywith respect to a reference sequence.
Author: Martin Hölzer
Author-email: HoelzerM@rki.de
License: Apache License 2.0
Project-URL: Bug Tracker, https://gitlab.com/RKIBioinformaticsPipelines/president/-/issues
Project-URL: Source Code, https://gitlab.com/RKIBioinformaticsPipelines/president
Project-URL: Related Software, https://gitlab.com/RKIBioinformaticsPipelines
Keywords: sequence alignment,corona,pblat,SARS-COV2
Classifier: Programming Language :: Python
Classifier: Programming Language :: Python :: 3.8
Classifier: Programming Language :: Python :: Implementation :: PyPy
Requires-Python: >=3.8.0
License-File: LICENSE
Requires-Dist: pandas
Requires-Dist: screed
Requires-Dist: numpy
